vinorm/__init__.py
vinorm/input.txt
vinorm/main
vinorm/output.txt
vinorm/vinorm.py
vinorm/Dict/Popular.txt
vinorm/Mapping/Acronyms.txt
vinorm/Mapping/Acronyms_shorten.txt
vinorm/Mapping/BaseUnit.txt
vinorm/Mapping/CurrencyUnit.txt
vinorm/Mapping/LetterSoundEN.txt
vinorm/Mapping/LetterSoundVN.txt
vinorm/Mapping/Number.txt
vinorm/Mapping/PrefixUnit.txt
vinorm/Mapping/Symbol.txt
vinorm/Mapping/Teencode.txt
vinorm/RegexRule/Codenumber.txt
vinorm/RegexRule/Date_1.txt
vinorm/RegexRule/Date_2.txt
vinorm/RegexRule/Date_3.txt
vinorm/RegexRule/Date_From_To_1.txt
vinorm/RegexRule/Date_From_To_2.txt
vinorm/RegexRule/Email.txt
vinorm/RegexRule/FootballOther.txt
vinorm/RegexRule/FootballUnder.txt
vinorm/RegexRule/Measurement.txt
vinorm/RegexRule/Measurement_1.txt
vinorm/RegexRule/Month.txt
vinorm/RegexRule/NormalNumber.txt
vinorm/RegexRule/Office.txt
vinorm/RegexRule/PhoneNumber.txt
vinorm/RegexRule/PoliticalDivision.txt
vinorm/RegexRule/RomanNumber.txt
vinorm/RegexRule/Street.txt
vinorm/RegexRule/Time.txt
vinorm/RegexRule/Website.txt
vinorm/lib/libicudata.so
vinorm/lib/libicudata.so.64
vinorm/lib/libicudata.so.64.2
vinorm/lib/libicui18n.so
vinorm/lib/libicui18n.so.64
vinorm/lib/libicui18n.so.64.2
vinorm/lib/libicuio.so
vinorm/lib/libicuio.so.64
vinorm/lib/libicuio.so.64.2
vinorm/lib/libicutest.so
vinorm/lib/libicutest.so.64
vinorm/lib/libicutest.so.64.2
vinorm/lib/libicutu.so
vinorm/lib/libicutu.so.64
vinorm/lib/libicutu.so.64.2
vinorm/lib/libicuuc.so
vinorm/lib/libicuuc.so.64
vinorm/lib/libicuuc.so.64.2
vinorm/lib/icu/64.2/Makefile.inc
vinorm/lib/icu/64.2/pkgdata.inc
vinorm/lib/pkgconfig/icu-i18n.pc
vinorm/lib/pkgconfig/icu-io.pc
vinorm/lib/pkgconfig/icu-uc.pc
vinorm-2.0.7.dist-info/LICENSE
vinorm-2.0.7.dist-info/METADATA
vinorm-2.0.7.dist-info/WHEEL
vinorm-2.0.7.dist-info/top_level.txt
vinorm-2.0.7.dist-info/RECORD
