Metadata-Version: 2.1
Name: vinorm
Version: 2.0.7
Summary: Python package for text normalization, use for frontend of Text-to-speech Reseach
Home-page: https://github.com/NoahDrisort/vinorm
Author: AILAB
Author-email: donhanbentre@gmail.com
License: AILAB
Platform: UNKNOWN
Classifier: Development Status :: 4 - Beta
Classifier: License :: Free for non-commercial use
Classifier: Natural Language :: Vietnamese
Classifier: Operating System :: POSIX :: Linux
Classifier: Programming Language :: C++
Classifier: Programming Language :: Python :: 3.6
Classifier: Topic :: Scientific/Engineering :: Artificial Intelligence
